{
    "id": "unit29",
    "name": "Unit 29: How many bottles are there?",
    "description": "Learn 'How many...?', colours, and yes/no questions.",
    "thumbnail": "Images/Unit29/unit29_thumbnail.jpg",
    "words": [
      {
        "image": "Images/Unit29/1.webp",
        "audio": "Audio/Unit29/01_Chapter 1.mp3",
        "text": ""
      },
      {
        "image": "Images/Unit29/2.webp",
        "audio": "Audio/Unit29/02_Chapter 1.mp3",
        "text": ""
      },
      {
        "image": "Images/repeating_assets/looklisten.webp",
        "audio": "Audio/intro2/looklistenrepeat.mp3",
        "text": ""
      },
  
      {
        "image": "Images/Unit29/4.webp",
        "audio": "Audio/Unit29/04_Chapter 1.mp3",
        "text": "How many bottles are there?"
      },
      {
        "image": "Images/Unit29/4.webp",
        "audio": "Audio/Unit29/05_Chapter 1.mp3",
        "text": "There are four bottles."
      },
  
      {
        "image": "Images/Unit29/6.webp",
        "audio": "Audio/Unit29/06_Chapter 1.mp3",
        "text": "How many candles are there?"
      },
      {
        "image": "Images/Unit29/6.webp",
        "audio": "Audio/Unit29/07_Chapter 1.mp3",
        "text": "There are three candles."
      },
  
      {
        "image": "Images/Unit29/8.webp",
        "audio": "Audio/Unit29/08_Chapter 1.mp3",
        "text": "How many flowers are there?"
      },
      {
        "image": "Images/Unit29/8.webp",
        "audio": "Audio/Unit29/09_Chapter 1.mp3",
        "text": "There are five flowers."
      },
  
      {
        "image": "Images/Unit29/10.webp",
        "audio": "Audio/Unit29/10_Chapter 1.mp3",
        "text": "How many alarm clocks are there?"
      },
      {
        "image": "Images/Unit29/10.webp",
        "audio": "Audio/Unit29/11_Chapter 1.mp3",
        "text": "There are two alarm clocks."
      },
  
      {
        "image": "Images/Unit29/12.webp",
        "audio": "Audio/Unit29/12_Chapter 1.mp3",
        "text": "How many boxes are there?"
      },
      {
        "image": "Images/Unit29/12.webp",
        "audio": "Audio/Unit29/13_Chapter 1.mp3",
        "text": "There are four boxes."
      },
  
      {
        "image": "Images/Unit29/14.webp",
        "audio": "Audio/Unit29/14_Chapter 1.mp3",
        "text": "How many headphones are there?"
      },
      {
        "image": "Images/Unit29/14.webp",
        "audio": "Audio/Unit29/15_Chapter 1.mp3",
        "text": "There are three headphones."
      },
  
      {
        "image": "Images/Unit29/16.webp",
        "audio": "Audio/Unit29/16_Chapter 1.mp3",
        "text": "How many bags are there?"
      },
      {
        "image": "Images/Unit29/16.webp",
        "audio": "Audio/Unit29/17_Chapter 1.mp3",
        "text": "There are five bags."
      },
  
      {
        "image": "Images/Unit29/18.webp",
        "audio": "Audio/Unit29/18_Chapter 1.mp3",
        "text": "What colours are they?"
      },
      {
        "image": "Images/Unit29/18.webp",
        "audio": "Audio/Unit29/19_Chapter 1.mp3",
        "text": "They are yellow, green and red."
      },
  
      {
        "image": "Images/Unit29/20.webp",
        "audio": "Audio/Unit29/20_Chapter 1.mp3",
        "text": "How many yellow bags are there?"
      },
      {
        "image": "Images/Unit29/20.webp",
        "audio": "Audio/Unit29/21_Chapter 1.mp3",
        "text": "There are three yellow bags."
      },
  
      {
        "image": "Images/Unit29/22.webp",
        "audio": "Audio/Unit29/22_Chapter 1.mp3",
        "text": "Is there a blue bag?"
      },
      {
        "image": "Images/Unit29/22.webp",
        "audio": "Audio/Unit29/23_Chapter 1.mp3",
        "text": "No, there isn't."
      },
  
      {
        "image": "Images/Unit29/24.webp",
        "audio": "Audio/Unit29/24_Chapter 1.mp3",
        "text": "Is there a red bag?"
      },
      {
        "image": "Images/Unit29/24.webp",
        "audio": "Audio/Unit29/25_Chapter 1.mp3",
        "text": "Yes, there is."
      },
  
      {
        "image": "Images/Unit29/26.webp",
        "audio": "Audio/Unit29/26_Chapter 1.mp3",
        "text": "Is there a white bag?"
      },
      {
        "image": "Images/Unit29/26.webp",
        "audio": "Audio/Unit29/27_Chapter 1.mp3",
        "text": "No, there isn't."
      },
  
      {
        "image": "Images/Unit29/28.webp",
        "audio": "Audio/Unit29/28_Chapter 1.mp3",
        "text": "Is there a green bag?"
      },
      {
        "image": "Images/Unit29/28.webp",
        "audio": "Audio/Unit29/29_Chapter 1.mp3",
        "text": "Yes, there is."
      },
  
      {
        "image": "Images/Unit29/30.webp",
        "audio": "Audio/Unit29/30_Chapter 1.mp3",
        "text": ""
      }
    ]
  }
  