{
  "id": "unit20",
  "name": "Unit 20: Here and There",
  "description": "Learn to use here and there in simple sentences.",
  "thumbnail": "Images/Unit20/unit20_thumbnail.jpg",
  "words": [
    {
      "image": "Images/Unit20/1.webp",
      "audio": "Audio/Unit20/01_Chapter 1.mp3",
      "text": ""
    },
    {
      "image": "Images/Unit20/2.webp",
      "audio": "Audio/Unit20/02_Chapter 1.mp3",
      "text": ""
    },
    {
      "image": "Images/Unit20/3.webp",
      "audio": "Audio/intro2/looklistenrepeat.mp3",
      "text": ""
    },
    {
      "image": "Images/Unit20/4.webp",
      "audio": "Audio/Unit20/04_Chapter 1.mp3",
      "text": "Manku's cap is here. Raju's T\u2011Shirt is there."

    },
    {
      "image": "Images/Unit20/5.webp",
      "audio": "Audio/Unit20/05_Chapter 1.mp3",
      "text": "The red water bottle is here. The white water bottle is there."
    },
    {
      "image": "Images/Unit20/6.webp",
      "audio": "Audio/Unit20/06_Chapter 1.mp3",
      "text": "The apples are here. The bananas are there."
    },
    {
      "image": "Images/Unit20/7.webp",
      "audio": "Audio/Unit20/07_Chapter 1.mp3",
      "text": "The black shoes are here. The pink shoes are there."
    },
    {
      "image": "Images/Unit20/8.webp",
      "audio": "Audio/Unit20/08_Chapter 1.mp3",
      "text": "The white socks are here. The black socks are there."
    },
    {
      "image": "Images/Unit20/9.webp",
      "audio": "Audio/Unit20/09_Chapter 1.mp3",
      "text": "The pencil is here. The notebook is there."
    },
    {
      "image": "Images/Unit20/10.webp",
      "audio": "Audio/Unit20/10_Chapter 1.mp3",
      "text": "The pineapple is here. The mangoes are there."
    },
    {
      "image": "Images/Unit20/11.webp",
      "audio": "Audio/Unit20/11_Chapter 1.mp3",
      "text": "Manku is here. Raju is there."
    },
    {
      "image": "Images/Unit20/12.webp",
      "audio": "Audio/Unit20/12_Chapter 1.mp3",
      "text": "Where is Saira?"
    },
    {
      "image": "Images/Unit20/13.webp",
      "audio": "Audio/Unit20/13_Chapter 1.mp3",
      "text": "She is here."
    },
    {
      "image": "Images/Unit20/14.webp",
      "audio": "Audio/Unit20/14_Chapter 1.mp3",
      "text": "Where is John?"
    },
    {
      "image": "Images/Unit20/15.webp",
      "audio": "Audio/Unit20/15_Chapter 1.mp3",
      "text": "He is there."
    },
    {
      "image": "Images/Unit20/16.webp",
      "audio": "Audio/Unit20/16_Chapter 1.mp3",
      "text": "Where is Reena?"
    },
    {
      "image": "Images/Unit20/17.webp",
      "audio": "Audio/Unit20/17_Chapter 1.mp3",
      "text": "She is here."
    },
    {
      "image": "Images/Unit20/18.webp",
      "audio": "Audio/Unit20/18_Chapter 1.mp3",
      "text": "Where is Manku?"
    },
    {
      "image": "Images/Unit20/19.webp",
      "audio": "Audio/Unit20/19_Chapter 1.mp3",
      "text": "He is there."
    },
    {
      "image": "Images/Unit20/20.webp",
      "audio": "Audio/Unit20/20_Chapter 1.mp3",
      "text": ""
    }
  ]
}
